freetext_jupyter/__init__.py
freetext_jupyter-0.1.0.dist-info/METADATA
freetext_jupyter-0.1.0.dist-info/WHEEL
freetext_jupyter-0.1.0.dist-info/RECORD
