Metadata-Version: 2.1
Name: freetext-jupyter
Version: 0.1.0
Summary: Freeform text feedback using kordinglab/freetext-server.
License: Apache 2.0
Author: Jordan Matelsky
Author-email: opensource@matelsky.com
Requires-Python: >=3.9,<4.0
Classifier: License :: Other/Proprietary License
Classifier: Programming Language :: Python :: 3
Classifier: Programming Language :: Python :: 3.9
Classifier: Programming Language :: Python :: 3.10
Classifier: Programming Language :: Python :: 3.11
Requires-Dist: ipywidgets (>=8.0.6,<9.0.0)
Requires-Dist: requests (>=2.31.0,<3.0.0)
